fs_uae_wrapper/__init__.py
fs_uae_wrapper/archive.py
fs_uae_wrapper/base.py
fs_uae_wrapper/cd32.py
fs_uae_wrapper/file_archive.py
fs_uae_wrapper/message.py
fs_uae_wrapper/path.py
fs_uae_wrapper/plain.py
fs_uae_wrapper/savestate.py
fs_uae_wrapper/utils.py
fs_uae_wrapper/whdload.py
fs_uae_wrapper/wrapper.py
fs_uae_wrapper-0.10.5.dist-info/licenses/LICENSE
fs_uae_wrapper-0.10.5.dist-info/METADATA
fs_uae_wrapper-0.10.5.dist-info/WHEEL
fs_uae_wrapper-0.10.5.dist-info/entry_points.txt
fs_uae_wrapper-0.10.5.dist-info/top_level.txt
fs_uae_wrapper-0.10.5.dist-info/RECORD
