Metadata-Version: 2.4
Name: fs-uae-wrapper
Version: 0.10.5
Summary: Automate archives support and state saves for fs-uae
Author-email: Roman Dobosz <gryf73@gmail.com>
License-Expression: BSD-3-Clause
Project-URL: Homepage, https://github.com/gryf/fs-uae-wrapper
Keywords: uae,fs-uae,amiga,emulator,wrapper
Classifier: Development Status :: 5 - Production/Stable
Classifier: Environment :: Console
Classifier: Intended Audience :: End Users/Desktop
Classifier: Operating System :: OS Independent
Classifier: Programming Language :: Python :: 3
Classifier: Programming Language :: Python :: 3.8
Classifier: Programming Language :: Python :: 3.9
Classifier: Programming Language :: Python :: 3.10
Classifier: Programming Language :: Python :: 3.11
Classifier: Programming Language :: Python :: 3.12
Classifier: Topic :: System :: Emulators
Classifier: Topic :: Games/Entertainment
Requires-Python: >=3.8
License-File: LICENSE
Dynamic: license-file
